cache_purge_hooks/__init__.py
cache_purge_hooks/manager.py
cache_purge_hooks/shortcuts.py
cache_purge_hooks/utils.py
cache_purge_hooks/backends/__init__.py
cache_purge_hooks/backends/dumbnginxbackend.py
cache_purge_hooks/backends/dummy.py
cache_purge_hooks/backends/nginxbackend.py
cache_purge_hooks/backends/varnishbackend.py
django_cache_purge_hooks-0.5.1.dist-info/DESCRIPTION.rst
django_cache_purge_hooks-0.5.1.dist-info/METADATA
django_cache_purge_hooks-0.5.1.dist-info/RECORD
django_cache_purge_hooks-0.5.1.dist-info/WHEEL
django_cache_purge_hooks-0.5.1.dist-info/metadata.json
django_cache_purge_hooks-0.5.1.dist-info/top_level.txt
sampleproject/__init__.py
sampleproject/settings.py
sampleproject/sample/__init__.py
sampleproject/sample/models.py
