Metadata-Version: 2.0
Name: django-cache-purge-hooks
Version: 0.5.1
Summary: Drop-in cache (e.g. varnish) purging hooks for django
Home-page: https://github.com/RealGeeks/django-cache-purge-hooks
Author: Shu Zong Chen
Author-email: shu.chen@freelancedreams.com
License: MIT
Keywords: django cache purge varnish nginx
Platform: UNKNOWN
Classifier: Development Status :: 5 - Production/Stable
Classifier: Environment :: Web Environment
Classifier: Framework :: Django
Classifier: Intended Audience :: Developers
Classifier: License :: OSI Approved :: MIT License
Classifier: Operating System :: OS Independent
Classifier: Programming Language :: Python
Classifier: Topic :: Software Development :: Libraries :: Application Frameworks
Classifier: Topic :: Software Development :: Libraries :: Python Modules
Requires-Dist: requests
